{
  "index": "Homepage",
  "research": "Research",
  "spacex": "SpaceX",
  "xai": "xAI",
  "tesla": "Tesla",
  "neuralink": "Neuralink",
  "x": "X",
  "theoretical-foundations": "Theoretical Foundations",
  "mathematical-justifications": "Mathematical Justifications",
  "prototypes": "Prototypes",
  "3d-printing": "3D-Printing",
  "nano-assembly": "Nano-Assembly",
  "energy": "Energy",
  "computing": "Computing",
  "ai": "AI",
  "robots": "Robots",
  "theoretical-physics": "Theoretical Physics",
  "space": "Space",
  "consciousness": "Consciousness",
  "propulsion": "Propulsion",
  "particle-accelerators": "Particle Accelerators",
  "quantum": "Quantum",
  "regulative-governing-bodies": "Regulative / Governing Bodies",
  "standardization-certification-bodies": "Standardization / Certification bodies",
  "culture": "Culture",
  "roles": "Roles",
  "mission": {
    "title": "Mission",
    "type": "page"
  },
  "about": {
    "title": "About",
    "type": "page"
  },
  "contact": {
    "title": "Contact ↗",
    "type": "page",
    "href": "https://github.com/skyisuniverse",
    "newWindow": true
  }
}
